dagian/__init__.py
dagian/bundling.py
dagian/dag.py
dagian/data_definition.py
dagian/data_generator.py
dagian/data_handlers.py
dagian/decorators.py
dagian/data_wrappers/__init__.py
dagian/data_wrappers/pandas_hdf.py
dagian/data_wrappers/tests/__init__.py
dagian/data_wrappers/tests/test_pandas_hdf.py
dagian/tests/__init__.py
dagian/tests/lifetime_feature_generator.py
dagian/tests/test_feature_generator.py
dagian/tools/__init__.py
dagian/tools/config.py
dagian/tools/dag.py
dagian/tools/dagian_runner.py
dagian/utils/__init__.py
dagian/utils/frozen_dict.py
dagian/utils/tests/__init__.py
dagian/utils/tests/test_frozen_dict.py
dagian-0.0.3.dist-info/LICENSE
dagian-0.0.3.dist-info/METADATA
dagian-0.0.3.dist-info/WHEEL
dagian-0.0.3.dist-info/entry_points.txt
dagian-0.0.3.dist-info/top_level.txt
dagian-0.0.3.dist-info/RECORD
